agent/__init__.py
agent/main.py
scrathagent-0.1.0.dist-info/METADATA
scrathagent-0.1.0.dist-info/WHEEL
scrathagent-0.1.0.dist-info/top_level.txt
scrathagent-0.1.0.dist-info/RECORD
