Metadata-Version: 2.4
Name: scrathagent
Version: 0.1.0
Summary: A concise and informative description of your project.
Author-email: Qaadir <qaadireng@gmail.com>
License: MIT
Project-URL: Homepage, https://github.com/your-username/scrathagent
Project-URL: Bug Tracker, https://github.com/your-username/scrathagent/issues
Keywords: agent
Classifier: Development Status :: 3 - Alpha
Classifier: Intended Audience :: Developers
Classifier: License :: OSI Approved :: MIT License
Classifier: Programming Language :: Python :: 3
Classifier: Programming Language :: Python :: 3.13
Requires-Python: >=3.13
Requires-Dist: build>=1.3.0
Requires-Dist: requests>=2.20.0
Requires-Dist: twine>=6.2.0
